minidisc.py
minidisc_python-0.1.1.dist-info/METADATA
minidisc_python-0.1.1.dist-info/WHEEL
minidisc_python-0.1.1.dist-info/top_level.txt
minidisc_python-0.1.1.dist-info/RECORD
