Metadata-Version: 2.4
Name: minidisc-python
Version: 0.1.1
Summary: Minidisc Python library
Author-email: Matthias Scheidegger <mscheidegger@gmail.com>
Project-URL: Homepage, https://github.com/mscheidegger/minidisc
Project-URL: Repository, https://github.com/mscheidegger/minidisc.git
Requires-Python: >=3.7
Requires-Dist: pydantic<3,>=2.0
